README.md
cdh_lava_demo/__init__.py
cdh_lava_demo/__main__.py
cdh_lava_demo/aws_storage_service/__init__.py
cdh_lava_demo/aws_storage_service/aws_storage_file.py
cdh_lava_demo/az_key_vault_service/__init__.py
cdh_lava_demo/az_key_vault_service/az_key_vault.py
cdh_lava_demo/az_storage_service/__init__.py
cdh_lava_demo/az_storage_service/az_storage_file.py
cdh_lava_demo/az_storage_service/az_storage_queue.py
cdh_lava_demo/cdc_log_service/__init__.py
cdh_lava_demo/cdc_log_service/environment_logging.py
cdh_lava_demo/cdc_log_service/environment_tracing.py
cdh_lava_demo/cdc_log_service/sequence_diagram.py
cdh_lava_demo/cdc_metadata_service/__init__.py
cdh_lava_demo/cdc_metadata_service/environment_metadata.py
cdh_lava_demo/cdc_security_service/__init__.py
cdh_lava_demo/cdc_security_service/security_base64.py
cdh_lava_demo/cdc_security_service/security_core.py
cdh_lava_demo/cdc_tech_environment_service/__init__.py
cdh_lava_demo/cdc_tech_environment_service/environment_core.py
cdh_lava_demo/cdc_tech_environment_service/environment_file.py
cdh_lava_demo/cdc_tech_environment_service/environment_http.py
cdh_lava_demo/cdc_tech_environment_service/environment_spark.py
cdh_lava_demo/cdc_tech_environment_service/environment_string.py
cdh_lava_demo/cdc_tech_environment_service/environment_tar.py
cdh_lava_demo/cdc_tech_environment_service/job_core.py
cdh_lava_demo/databricks_service/notebook.py
cdh_lava_demo/databricks_service/repo_core.py
cdh_lava_demo/dbx_accelerator/__init__.py
cdh_lava_demo/dbx_accelerator/common/__init__.py
cdh_lava_demo/dbx_accelerator/common/cloud.py
cdh_lava_demo/dbx_accelerator/common/validator.py
cdh_lava_demo/dbx_accelerator/companion.py
cdh_lava_demo/dbx_accelerator/dbgems/__init__.py
cdh_lava_demo/dbx_accelerator/dbgems/mock_dbutils_class.py
cdh_lava_demo/dbx_accelerator/dbgems/mock_spark_context_class.py
cdh_lava_demo/dbx_accelerator/sol_acc_util.py
cdh_lava_demo/dbx_db_rest/__init__.py
cdh_lava_demo/dbx_db_rest/cluster_policies.py
cdh_lava_demo-202402.0.20.dist-info/METADATA
cdh_lava_demo-202402.0.20.dist-info/WHEEL
cdh_lava_demo-202402.0.20.dist-info/entry_points.txt
cdh_lava_demo-202402.0.20.dist-info/RECORD
